ofxstatement_zm_stanbic-1.1.1-nspkg.pth
ofxstatement/plugins/stanbiczm.py
ofxstatement_zm_stanbic-1.1.1.dist-info/LICENSE
ofxstatement_zm_stanbic-1.1.1.dist-info/METADATA
ofxstatement_zm_stanbic-1.1.1.dist-info/WHEEL
ofxstatement_zm_stanbic-1.1.1.dist-info/entry_points.txt
ofxstatement_zm_stanbic-1.1.1.dist-info/namespace_packages.txt
ofxstatement_zm_stanbic-1.1.1.dist-info/top_level.txt
ofxstatement_zm_stanbic-1.1.1.dist-info/zip-safe
ofxstatement_zm_stanbic-1.1.1.dist-info/RECORD
